polars_avro-0.7.1.dist-info/METADATA
polars_avro-0.7.1.dist-info/WHEEL
polars_avro-0.7.1.dist-info/licenses/LICENSE
polars_avro/__init__.py
polars_avro/_avro_rs.abi3.so
polars_avro/_avro_rs.pyi
polars_avro/_scan.py
polars_avro/_sink.py
polars_avro/py.typed
polars_avro-0.7.1.dist-info/RECORD
