Metadata-Version: 2.4
Name: polars-avro
Version: 0.7.1
Requires-Dist: polars>=1.13.0
Requires-Dist: pyarrow>=7.0.0
License-File: LICENSE
Summary: Polars io-plugin for reading and writing avro files
Requires-Python: >=3.10
